ap_rss_reader/__init__.py
ap_rss_reader/__main__.py
ap_rss_reader/ap_collections.py
ap_rss_reader/ap_constants.py
ap_rss_reader/ap_typing.py
ap_rss_reader/cli.py
ap_rss_reader/log.py
ap_rss_reader/py.typed
ap_rss_reader/rss_channel.py
ap_rss_reader/utils.py
ap_rss_reader-0.0.3.dist-info/LICENSE.txt
ap_rss_reader-0.0.3.dist-info/METADATA
ap_rss_reader-0.0.3.dist-info/WHEEL
ap_rss_reader-0.0.3.dist-info/entry_points.txt
ap_rss_reader-0.0.3.dist-info/top_level.txt
ap_rss_reader-0.0.3.dist-info/RECORD
