Metadata-Version: 2.1
Name: ap-rss-reader
Version: 0.0.3
Summary: AP RSS-reader with CLI.
Home-page: https://github.com/aplatkouski/ap-rss-reader
Author: Artsiom Platkouski
Author-email: komukc.apt@gmail.com
License: MIT
Project-URL: Bug Reports, https://github.com/aplatkouski/ap-rss-reader/issues
Project-URL: Source, https://github.com/aplatkouski/ap-rss-reader
Keywords: rss reader,console application
Platform: UNKNOWN
Classifier: Development Status :: 4 - Beta
Classifier: Environment :: Console
Classifier: Intended Audience :: Developers
Classifier: Intended Audience :: End Users/Desktop
Classifier: License :: OSI Approved :: MIT License
Classifier: Natural Language :: English
Classifier: Operating System :: OS Independent
Classifier: Programming Language :: Python
Classifier: Programming Language :: Python :: 3
Classifier: Programming Language :: Python :: 3 :: Only
Classifier: Programming Language :: Python :: 3.8
Classifier: Programming Language :: Python :: Implementation :: CPython
Classifier: Topic :: Software Development :: Libraries :: Python Modules
Requires-Python: <4,>=3.8
Requires-Dist: beautifulsoup4 (==4.9.3)
Requires-Dist: lxml (==4.6.3)
Requires-Dist: python-dateutil (==2.8.1)
Requires-Dist: requests (==2.25.1)
Requires-Dist: xhtml2pdf (==0.2.5)
Provides-Extra: dev
Requires-Dist: black (==21.5b1) ; extra == 'dev'
Requires-Dist: bump2version (==1.0.1) ; extra == 'dev'
Requires-Dist: check-manifest (==0.46) ; extra == 'dev'
Requires-Dist: darglint (==1.8.0) ; extra == 'dev'
Requires-Dist: flake8 (==3.9.2) ; extra == 'dev'
Requires-Dist: flake8-bugbear (==21.4.3) ; extra == 'dev'
Requires-Dist: flake8-docstrings (==1.6.0) ; extra == 'dev'
Requires-Dist: flake8-pytest-style (==1.4.2) ; extra == 'dev'
Requires-Dist: flake8-typing-imports (==1.10.1) ; extra == 'dev'
Requires-Dist: gitlint (==0.15.1) ; extra == 'dev'
Requires-Dist: isort (==5.8.0) ; extra == 'dev'
Requires-Dist: mypy (==0.812) ; extra == 'dev'
Requires-Dist: mypy-extensions (==0.4.3) ; extra == 'dev'
Requires-Dist: pre-commit (==2.13.0) ; extra == 'dev'
Requires-Dist: pre-commit-hooks (==4.0.1) ; extra == 'dev'
Requires-Dist: pydocstyle (==6.1.1) ; extra == 'dev'
Requires-Dist: pylint (==2.8.2) ; extra == 'dev'
Requires-Dist: pyupgrade (==2.19.0) ; extra == 'dev'
Requires-Dist: tox (==3.23.1) ; extra == 'dev'
Requires-Dist: twine (==3.4.1) ; extra == 'dev'
Provides-Extra: test
Requires-Dist: coverage (==5.5) ; extra == 'test'
Requires-Dist: pytest (==6.2.4) ; extra == 'test'
